MANIFEST.in
README.txt
setup.cfg
setup.py
rbco/__init__.py
rbco.msexcel.egg-info/PKG-INFO
rbco.msexcel.egg-info/SOURCES.txt
rbco.msexcel.egg-info/dependency_links.txt
rbco.msexcel.egg-info/entry_points.txt
rbco.msexcel.egg-info/namespace_packages.txt
rbco.msexcel.egg-info/not-zip-safe
rbco.msexcel.egg-info/requires.txt
rbco.msexcel.egg-info/top_level.txt
rbco/msexcel/README.txt
rbco/msexcel/__init__.py