Metadata-Version: 1.1
Name: rbco.msexcel
Version: 0.0.3
Summary: Provide functions to read, parse and convert MS Excel spreadsheets into various data structures.
Home-page: UNKNOWN
Author: Rafael Oliveira
Author-email: rafaelbco@gmail.com
License: GPL
Keywords: xls excel
Platform: UNKNOWN
Classifier: Programming Language :: Python
Classifier: Topic :: Software Development :: Libraries :: Python Modules
